ermiaoweb-0.0.1.dist-info/DESCRIPTION.rst
ermiaoweb-0.0.1.dist-info/metadata.json
ermiaoweb-0.0.1.dist-info/top_level.txt
ermiaoweb-0.0.1.dist-info/METADATA
ermiaoweb-0.0.1.dist-info/WHEEL
ermiaoweb-0.0.1.dist-info/RECORD
ermiaoweb/__init__.py
ermiaoweb/core/http.py
ermiaoweb/core/__init__.py
ermiaoweb/core/views.py
ermiaoweb/core/app.py
